mini_judge/__init__.py
mini_judge/data_io.py
mini_judge/example_data/candidate_answers.jsonl
mini_judge/example_data/questions.jsonl
mini_judge/example_data/ref_answers.jsonl
mini_judge/judge_execution.py
mini_judge/judge_prompt.py
mini_judge/main.py
mini_judge/trial_result_manager.py
mini_judge-0.4.1.dist-info/LICENSE
mini_judge-0.4.1.dist-info/WHEEL
mini_judge-0.4.1.dist-info/METADATA
mini_judge-0.4.1.dist-info/entry_points.txt
mini_judge-0.4.1.dist-info/RECORD
