Metadata-Version: 2.1
Name: mini-judge
Version: 0.4.1
Summary: 
Author: mrcabbage972
Requires-Python: >=3.9,<4.0
Classifier: Programming Language :: Python :: 3
Classifier: Programming Language :: Python :: 3.9
Classifier: Programming Language :: Python :: 3.10
Classifier: Programming Language :: Python :: 3.11
Requires-Dist: loguru (>=0.7.2,<0.8.0)
Requires-Dist: openai (>=0.28.1,<0.29.0)
Requires-Dist: python-dotenv (>=1.0.0,<2.0.0)
Requires-Dist: python-fire (>=0.1.0,<0.2.0)
Requires-Dist: tqdm (>=4.66.1,<5.0.0)
